[{"node":{"url":"eio_main/index.html","kind":"leaf-page","content":"eio_main"},"children":[{"node":{"url":null,"kind":null,"content":"Library <code>eio_main</code>"},"children":[{"node":{"url":"eio_main/eio_main/Eio_main/index.html","kind":"module","content":"Eio_main"},"children":[]}]},{"node":{"url":"eio_main/src/index.html","kind":"leaf-page","content":"Sources"},"children":[{"node":{"url":null,"kind":null,"content":"eio_main"},"children":[{"node":{"url":"eio_main/src/eio_main/eio_main.ml.html","kind":"source","content":"eio_main.ml"},"children":[]},{"node":{"url":"eio_main/src/eio_main/eio_main__.ml.html","kind":"source","content":"eio_main__.ml"},"children":[]},{"node":{"url":"eio_main/src/eio_main/linux_backend.ml.html","kind":"source","content":"linux_backend.ml"},"children":[]},{"node":{"url":"eio_main/src/eio_main/posix_backend.ml.html","kind":"source","content":"posix_backend.ml"},"children":[]},{"node":{"url":"eio_main/src/eio_main/windows_backend.ml.html","kind":"source","content":"windows_backend.ml"},"children":[]}]}]}]}]