[{"node":{"url":"biniou/index.html","kind":"leaf-page","content":"biniou"},"children":[{"node":{"url":null,"kind":null,"content":"Library <code>biniou</code>"},"children":[{"node":{"url":"biniou/biniou/Bi_dump/index.html","kind":"module","content":"Bi_dump"},"children":[]},{"node":{"url":"biniou/biniou/Bi_inbuf/index.html","kind":"module","content":"Bi_inbuf"},"children":[]},{"node":{"url":"biniou/biniou/Bi_io/index.html","kind":"module","content":"Bi_io"},"children":[]},{"node":{"url":"biniou/biniou/Bi_outbuf/index.html","kind":"module","content":"Bi_outbuf"},"children":[]},{"node":{"url":"biniou/biniou/Bi_share/index.html","kind":"module","content":"Bi_share"},"children":[]},{"node":{"url":"biniou/biniou/Bi_stream/index.html","kind":"module","content":"Bi_stream"},"children":[]},{"node":{"url":"biniou/biniou/Bi_util/index.html","kind":"module","content":"Bi_util"},"children":[]},{"node":{"url":"biniou/biniou/Bi_vint/index.html","kind":"module","content":"Bi_vint"},"children":[]}]},{"node":{"url":"biniou/src/index.html","kind":"leaf-page","content":"Sources"},"children":[{"node":{"url":null,"kind":null,"content":"biniou"},"children":[{"node":{"url":"biniou/src/biniou/bi_dump.ml.html","kind":"source","content":"bi_dump.ml"},"children":[]},{"node":{"url":"biniou/src/biniou/bi_inbuf.ml.html","kind":"source","content":"bi_inbuf.ml"},"children":[]},{"node":{"url":"biniou/src/biniou/bi_io.ml.html","kind":"source","content":"bi_io.ml"},"children":[]},{"node":{"url":"biniou/src/biniou/bi_outbuf.ml.html","kind":"source","content":"bi_outbuf.ml"},"children":[]},{"node":{"url":"biniou/src/biniou/bi_share.ml.html","kind":"source","content":"bi_share.ml"},"children":[]},{"node":{"url":"biniou/src/biniou/bi_stream.ml.html","kind":"source","content":"bi_stream.ml"},"children":[]},{"node":{"url":"biniou/src/biniou/bi_util.ml.html","kind":"source","content":"bi_util.ml"},"children":[]},{"node":{"url":"biniou/src/biniou/bi_vint.ml.html","kind":"source","content":"bi_vint.ml"},"children":[]}]}]}]}]